{"db_bench": {"mixgraph": {"name": "mixgraph", "latency": 7.682, "iops": 130179.0, "io_size": 75.0}}, "compaction_statistics": {"name": "CompactionStatistics", "overall_compaction_stats": {"uptime_secs": {"total": 900.5, "interval": 300.0}, "flush_gb": {"total": 0.209, "interval": 0.054}, "addfile_gb": {"total": 0.0, "interval": 0.0}, "addfile_total_files": {"total": 0, "interval": 0}, "addfile_l0_files": {"total": 0, "interval": 0}, "addfile_keys": {"total": 0, "interval": 0}, "cumulative_compaction": {"write_size_mb": 390.0, "write_throughput": 0.44, "read_size_mb": 340.0, "read_throughput": 0.38, "time_sec": 5.1}, "interval_compaction": {"write_size_mb": 100.0, "write_throughput": 0.36, "read_size_mb": 100.0, "read_throughput": 0.36, "time_sec": 1.4}, "stalls_count": {"level0_slowdown": 0, "level0_slowdown_with_compaction": 0, "level0_numfiles": 0, "level0_numfiles_with_compaction": 0, "stop": 0, "slowdown": 0, "memtable_compaction": 0, "memtable_slowdown": 7, "total": 2}}, "per_level_compaction_stats": [{"level": 0, "in_files": 0, "out_files": 1, "size_mb": 27.61, "score": 0.5, "read_gb": 0.0, "rn_gb": 0.0, "rnp1_gb": 0.0, "write_gb": 0.2, "wnew_gb": 0.2, "moved_gb": 0.0, "w_amp": 1.0, "rd_mb_per_s": 0.0, "wr_mb_per_s": 60.2, "comp_sec": 3.55, "comp_merge_cpu_sec": 3.26, "comp_cnt": 9.0, "avg_sec": 0.395, "key_in": 0.0, "key_drop": 0.0}, {"level": 1, "in_files": 0, "out_files": 1, "size_mb": 51.99, "score": 0.2, "read_gb": 0.3, "rn_gb": 0.2, "rnp1_gb": 0.1, "write_gb": 0.2, "wnew_gb": 0.1, "moved_gb": 0.0, "w_amp": 0.9, "rd_mb_per_s": 226.2, "wr_mb_per_s": 122.5, "comp_sec": 1.52, "comp_merge_cpu_sec": 1.39, "comp_cnt": 4.0, "avg_sec": 0.381, "key_in": 7.924, "key_drop": 3.564}]}, "file_read": [{"name": "FileReadStatsLevel0", "level": 0, "count": 19627, "average": 85.9385, "stddev": 167.38, "min": 51, "median": 68.477, "max": 6893, "p50": 68.48, "p75": 81.63, "p99": 479.44, "p99_9": 1851.64, "p99_99": 6893.0}, {"name": "FileReadStatsLevel1", "level": 1, "count": 17124, "average": 69.0487, "stddev": 95.46, "min": 50, "median": 66.092, "max": 6973, "p50": 66.09, "p75": 73.64, "p99": 187.47, "p99_9": 364.14, "p99_99": 6973.0}], "statistics": {"name": "RocksDBStatistics", "rocksdb_block_cache_miss": {"name": "rocksdb_block_cache_miss", "count": 51209}, "rocksdb_block_cache_hit": {"name": "rocksdb_block_cache_hit", "count": 133606807}, "rocksdb_block_cache_add": {"name": "rocksdb_block_cache_add", "count": 37948}, "rocksdb_block_cache_add_failures": {"name": "rocksdb_block_cache_add_failures", "count": 0}, "rocksdb_block_cache_index_miss": {"name": "rocksdb_block_cache_index_miss", "count": 0}, "rocksdb_block_cache_index_hit": {"name": "rocksdb_block_cache_index_hit", "count": 0}, "rocksdb_block_cache_index_add": {"name": "rocksdb_block_cache_index_add", "count": 0}, "rocksdb_block_cache_index_bytes_insert": {"name": "rocksdb_block_cache_index_bytes_insert", "count": 0}, "rocksdb_block_cache_index_bytes_evict": {"name": "rocksdb_block_cache_index_bytes_evict", "count": 0}, "rocksdb_block_cache_filter_miss": {"name": "rocksdb_block_cache_filter_miss", "count": 0}, "rocksdb_block_cache_filter_hit": {"name": "rocksdb_block_cache_filter_hit", "count": 0}, "rocksdb_block_cache_filter_add": {"name": "rocksdb_block_cache_filter_add", "count": 0}, "rocksdb_block_cache_filter_bytes_insert": {"name": "rocksdb_block_cache_filter_bytes_insert", "count": 0}, "rocksdb_block_cache_filter_bytes_evict": {"name": "rocksdb_block_cache_filter_bytes_evict", "count": 0}, "rocksdb_block_cache_data_miss": {"name": "rocksdb_block_cache_data_miss", "count": 51209}, "rocksdb_block_cache_data_hit": {"name": "rocksdb_block_cache_data_hit", "count": 133606807}, "rocksdb_block_cache_data_add": {"name": "rocksdb_block_cache_data_add", "count": 37948}, "rocksdb_block_cache_data_bytes_insert": {"name": "rocksdb_block_cache_data_bytes_insert", "count": 834424560}, "rocksdb_block_cache_bytes_read": {"name": "rocksdb_block_cache_bytes_read", "count": 3006730105264}, "rocksdb_block_cache_bytes_write": {"name": "rocksdb_block_cache_bytes_write", "count": 834424560}, "rocksdb_bloom_filter_useful": {"name": "rocksdb_bloom_filter_useful", "count": 0}, "rocksdb_bloom_filter_full_positive": {"name": "rocksdb_bloom_filter_full_positive", "count": 0}, "rocksdb_bloom_filter_full_true_positive": {"name": "rocksdb_bloom_filter_full_true_positive", "count": 0}, "rocksdb_bloom_filter_micros": {"name": "rocksdb_bloom_filter_micros", "count": 0}, "rocksdb_persistent_cache_hit": {"name": "rocksdb_persistent_cache_hit", "count": 0}, "rocksdb_persistent_cache_miss": {"name": "rocksdb_persistent_cache_miss", "count": 0}, "rocksdb_sim_block_cache_hit": {"name": "rocksdb_sim_block_cache_hit", "count": 0}, "rocksdb_sim_block_cache_miss": {"name": "rocksdb_sim_block_cache_miss", "count": 0}, "rocksdb_memtable_hit": {"name": "rocksdb_memtable_hit", "count": 0}, "rocksdb_memtable_miss": {"name": "rocksdb_memtable_miss", "count": 99588728}, "rocksdb_l0_hit": {"name": "rocksdb_l0_hit", "count": 1035}, "rocksdb_l1_hit": {"name": "rocksdb_l1_hit", "count": 12638604}, "rocksdb_l2andup_hit": {"name": "rocksdb_l2andup_hit", "count": 0}, "rocksdb_compaction_key_drop_new": {"name": "rocksdb_compaction_key_drop_new", "count": 3564035}, "rocksdb_compaction_key_drop_obsolete": {"name": "rocksdb_compaction_key_drop_obsolete", "count": 0}, "rocksdb_compaction_key_drop_range_del": {"name": "rocksdb_compaction_key_drop_range_del", "count": 0}, "rocksdb_compaction_key_drop_user": {"name": "rocksdb_compaction_key_drop_user", "count": 0}, "rocksdb_compaction_range_del_drop_obsolete": {"name": "rocksdb_compaction_range_del_drop_obsolete", "count": 0}, "rocksdb_compaction_optimized_del_drop_obsolete": {"name": "rocksdb_compaction_optimized_del_drop_obsolete", "count": 0}, "rocksdb_compaction_cancelled": {"name": "rocksdb_compaction_cancelled", "count": 0}, "rocksdb_number_keys_written": {"name": "rocksdb_number_keys_written", "count": 16403200}, "rocksdb_number_keys_read": {"name": "rocksdb_number_keys_read", "count": 99588728}, "rocksdb_number_keys_updated": {"name": "rocksdb_number_keys_updated", "count": 0}, "rocksdb_bytes_written": {"name": "rocksdb_bytes_written", "count": 1605605542}, "rocksdb_bytes_read": {"name": "rocksdb_bytes_read", "count": 543504477}, "rocksdb_number_db_seek": {"name": "rocksdb_number_db_seek", "count": 1171071}, "rocksdb_number_db_next": {"name": "rocksdb_number_db_next", "count": 658878581}, "rocksdb_number_db_prev": {"name": "rocksdb_number_db_prev", "count": 0}, "rocksdb_number_db_seek_found": {"name": "rocksdb_number_db_seek_found", "count": 1170801}, "rocksdb_number_db_next_found": {"name": "rocksdb_number_db_next_found", "count": 658878579}, "rocksdb_number_db_prev_found": {"name": "rocksdb_number_db_prev_found", "count": 0}, "rocksdb_db_iter_bytes_read": {"name": "rocksdb_db_iter_bytes_read", "count": 69709466266}, "rocksdb_no_file_closes": {"name": "rocksdb_no_file_closes", "count": 0}, "rocksdb_no_file_opens": {"name": "rocksdb_no_file_opens", "count": 14}, "rocksdb_no_file_errors": {"name": "rocksdb_no_file_errors", "count": 0}, "rocksdb_l0_slowdown_micros": {"name": "rocksdb_l0_slowdown_micros", "count": 0}, "rocksdb_memtable_compaction_micros": {"name": "rocksdb_memtable_compaction_micros", "count": 0}, "rocksdb_l0_num_files_stall_micros": {"name": "rocksdb_l0_num_files_stall_micros", "count": 0}, "rocksdb_stall_micros": {"name": "rocksdb_stall_micros", "count": 7643}, "rocksdb_db_mutex_wait_micros": {"name": "rocksdb_db_mutex_wait_micros", "count": 0}, "rocksdb_rate_limit_delay_millis": {"name": "rocksdb_rate_limit_delay_millis", "count": 0}, "rocksdb_num_iterators": {"name": "rocksdb_num_iterators", "count": 0}, "rocksdb_number_multiget_get": {"name": "rocksdb_number_multiget_get", "count": 0}, "rocksdb_number_multiget_keys_read": {"name": "rocksdb_number_multiget_keys_read", "count": 0}, "rocksdb_number_multiget_bytes_read": {"name": "rocksdb_number_multiget_bytes_read", "count": 0}, "rocksdb_number_deletes_filtered": {"name": "rocksdb_number_deletes_filtered", "count": 0}, "rocksdb_number_merge_failures": {"name": "rocksdb_number_merge_failures", "count": 0}, "rocksdb_bloom_filter_prefix_checked": {"name": "rocksdb_bloom_filter_prefix_checked", "count": 0}, "rocksdb_bloom_filter_prefix_useful": {"name": "rocksdb_bloom_filter_prefix_useful", "count": 0}, "rocksdb_number_reseeks_iteration": {"name": "rocksdb_number_reseeks_iteration", "count": 128035}, "rocksdb_getupdatessince_calls": {"name": "rocksdb_getupdatessince_calls", "count": 0}, "rocksdb_block_cachecompressed_miss": {"name": "rocksdb_block_cachecompressed_miss", "count": 0}, "rocksdb_block_cachecompressed_hit": {"name": "rocksdb_block_cachecompressed_hit", "count": 0}, "rocksdb_block_cachecompressed_add": {"name": "rocksdb_block_cachecompressed_add", "count": 0}, "rocksdb_block_cachecompressed_add_failures": {"name": "rocksdb_block_cachecompressed_add_failures", "count": 0}, "rocksdb_wal_synced": {"name": "rocksdb_wal_synced", "count": 0}, "rocksdb_wal_bytes": {"name": "rocksdb_wal_bytes", "count": 1605605542}, "rocksdb_write_self": {"name": "rocksdb_write_self", "count": 16403200}, "rocksdb_write_other": {"name": "rocksdb_write_other", "count": 0}, "rocksdb_write_timeout": {"name": "rocksdb_write_timeout", "count": 0}, "rocksdb_write_wal": {"name": "rocksdb_write_wal", "count": 16403200}, "rocksdb_compact_read_bytes": {"name": "rocksdb_compact_read_bytes", "count": 134935994}, "rocksdb_compact_write_bytes": {"name": "rocksdb_compact_write_bytes", "count": 217302505}, "rocksdb_flush_write_bytes": {"name": "rocksdb_flush_write_bytes", "count": 202638522}, "rocksdb_compact_read_marked_bytes": {"name": "rocksdb_compact_read_marked_bytes", "count": 0}, "rocksdb_compact_read_periodic_bytes": {"name": "rocksdb_compact_read_periodic_bytes", "count": 0}, "rocksdb_compact_read_ttl_bytes": {"name": "rocksdb_compact_read_ttl_bytes", "count": 0}, "rocksdb_compact_write_marked_bytes": {"name": "rocksdb_compact_write_marked_bytes", "count": 0}, "rocksdb_compact_write_periodic_bytes": {"name": "rocksdb_compact_write_periodic_bytes", "count": 0}, "rocksdb_compact_write_ttl_bytes": {"name": "rocksdb_compact_write_ttl_bytes", "count": 0}, "rocksdb_number_direct_load_table_properties": {"name": "rocksdb_number_direct_load_table_properties", "count": 0}, "rocksdb_number_superversion_acquires": {"name": "rocksdb_number_superversion_acquires", "count": 68}, "rocksdb_number_superversion_releases": {"name": "rocksdb_number_superversion_releases", "count": 7}, "rocksdb_number_superversion_cleanups": {"name": "rocksdb_number_superversion_cleanups", "count": 6}, "rocksdb_number_block_compressed": {"name": "rocksdb_number_block_compressed", "count": 37746}, "rocksdb_number_block_decompressed": {"name": "rocksdb_number_block_decompressed", "count": 51223}, "rocksdb_number_block_not_compressed": {"name": "rocksdb_number_block_not_compressed", "count": 0}, "rocksdb_merge_operation_time_nanos": {"name": "rocksdb_merge_operation_time_nanos", "count": 0}, "rocksdb_filter_operation_time_nanos": {"name": "rocksdb_filter_operation_time_nanos", "count": 0}, "rocksdb_row_cache_hit": {"name": "rocksdb_row_cache_hit", "count": 0}, "rocksdb_row_cache_miss": {"name": "rocksdb_row_cache_miss", "count": 0}, "rocksdb_read_amp_estimate_useful_bytes": {"name": "rocksdb_read_amp_estimate_useful_bytes", "count": 0}, "rocksdb_read_amp_total_read_bytes": {"name": "rocksdb_read_amp_total_read_bytes", "count": 0}, "rocksdb_number_rate_limiter_drains": {"name": "rocksdb_number_rate_limiter_drains", "count": 0}, "rocksdb_number_iter_skip": {"name": "rocksdb_number_iter_skip", "count": 282865833}, "rocksdb_blobdb_num_put": {"name": "rocksdb_blobdb_num_put", "count": 0}, "rocksdb_blobdb_num_write": {"name": "rocksdb_blobdb_num_write", "count": 0}, "rocksdb_blobdb_num_get": {"name": "rocksdb_blobdb_num_get", "count": 0}, "rocksdb_blobdb_num_multiget": {"name": "rocksdb_blobdb_num_multiget", "count": 0}, "rocksdb_blobdb_num_seek": {"name": "rocksdb_blobdb_num_seek", "count": 0}, "rocksdb_blobdb_num_next": {"name": "rocksdb_blobdb_num_next", "count": 0}, "rocksdb_blobdb_num_prev": {"name": "rocksdb_blobdb_num_prev", "count": 0}, "rocksdb_blobdb_num_keys_written": {"name": "rocksdb_blobdb_num_keys_written", "count": 0}, "rocksdb_blobdb_num_keys_read": {"name": "rocksdb_blobdb_num_keys_read", "count": 0}, "rocksdb_blobdb_bytes_written": {"name": "rocksdb_blobdb_bytes_written", "count": 0}, "rocksdb_blobdb_bytes_read": {"name": "rocksdb_blobdb_bytes_read", "count": 0}, "rocksdb_blobdb_write_inlined": {"name": "rocksdb_blobdb_write_inlined", "count": 0}, "rocksdb_blobdb_write_inlined_ttl": {"name": "rocksdb_blobdb_write_inlined_ttl", "count": 0}, "rocksdb_blobdb_write_blob": {"name": "rocksdb_blobdb_write_blob", "count": 0}, "rocksdb_blobdb_write_blob_ttl": {"name": "rocksdb_blobdb_write_blob_ttl", "count": 0}, "rocksdb_blobdb_blob_file_bytes_written": {"name": "rocksdb_blobdb_blob_file_bytes_written", "count": 0}, "rocksdb_blobdb_blob_file_bytes_read": {"name": "rocksdb_blobdb_blob_file_bytes_read", "count": 0}, "rocksdb_blobdb_blob_file_synced": {"name": "rocksdb_blobdb_blob_file_synced", "count": 0}, "rocksdb_blobdb_blob_index_expired_count": {"name": "rocksdb_blobdb_blob_index_expired_count", "count": 0}, "rocksdb_blobdb_blob_index_expired_size": {"name": "rocksdb_blobdb_blob_index_expired_size", "count": 0}, "rocksdb_blobdb_blob_index_evicted_count": {"name": "rocksdb_blobdb_blob_index_evicted_count", "count": 0}, "rocksdb_blobdb_blob_index_evicted_size": {"name": "rocksdb_blobdb_blob_index_evicted_size", "count": 0}, "rocksdb_blobdb_gc_num_files": {"name": "rocksdb_blobdb_gc_num_files", "count": 0}, "rocksdb_blobdb_gc_num_new_files": {"name": "rocksdb_blobdb_gc_num_new_files", "count": 0}, "rocksdb_blobdb_gc_failures": {"name": "rocksdb_blobdb_gc_failures", "count": 0}, "rocksdb_blobdb_gc_num_keys_overwritten": {"name": "rocksdb_blobdb_gc_num_keys_overwritten", "count": 0}, "rocksdb_blobdb_gc_num_keys_expired": {"name": "rocksdb_blobdb_gc_num_keys_expired", "count": 0}, "rocksdb_blobdb_gc_num_keys_relocated": {"name": "rocksdb_blobdb_gc_num_keys_relocated", "count": 0}, "rocksdb_blobdb_gc_bytes_overwritten": {"name": "rocksdb_blobdb_gc_bytes_overwritten", "count": 0}, "rocksdb_blobdb_gc_bytes_expired": {"name": "rocksdb_blobdb_gc_bytes_expired", "count": 0}, "rocksdb_blobdb_gc_bytes_relocated": {"name": "rocksdb_blobdb_gc_bytes_relocated", "count": 0}, "rocksdb_blobdb_fifo_num_files_evicted": {"name": "rocksdb_blobdb_fifo_num_files_evicted", "count": 0}, "rocksdb_blobdb_fifo_num_keys_evicted": {"name": "rocksdb_blobdb_fifo_num_keys_evicted", "count": 0}, "rocksdb_blobdb_fifo_bytes_evicted": {"name": "rocksdb_blobdb_fifo_bytes_evicted", "count": 0}, "rocksdb_txn_overhead_mutex_prepare": {"name": "rocksdb_txn_overhead_mutex_prepare", "count": 0}, "rocksdb_txn_overhead_mutex_old_commit_map": {"name": "rocksdb_txn_overhead_mutex_old_commit_map", "count": 0}, "rocksdb_txn_overhead_duplicate_key": {"name": "rocksdb_txn_overhead_duplicate_key", "count": 0}, "rocksdb_txn_overhead_mutex_snapshot": {"name": "rocksdb_txn_overhead_mutex_snapshot", "count": 0}, "rocksdb_txn_get_tryagain": {"name": "rocksdb_txn_get_tryagain", "count": 0}, "rocksdb_number_multiget_keys_found": {"name": "rocksdb_number_multiget_keys_found", "count": 0}, "rocksdb_num_iterator_created": {"name": "rocksdb_num_iterator_created", "count": 1171071}, "rocksdb_num_iterator_deleted": {"name": "rocksdb_num_iterator_deleted", "count": 1171071}, "rocksdb_block_cache_compression_dict_miss": {"name": "rocksdb_block_cache_compression_dict_miss", "count": 0}, "rocksdb_block_cache_compression_dict_hit": {"name": "rocksdb_block_cache_compression_dict_hit", "count": 0}, "rocksdb_block_cache_compression_dict_add": {"name": "rocksdb_block_cache_compression_dict_add", "count": 0}, "rocksdb_block_cache_compression_dict_bytes_insert": {"name": "rocksdb_block_cache_compression_dict_bytes_insert", "count": 0}, "rocksdb_block_cache_compression_dict_bytes_evict": {"name": "rocksdb_block_cache_compression_dict_bytes_evict", "count": 0}, "rocksdb_block_cache_add_redundant": {"name": "rocksdb_block_cache_add_redundant", "count": 0}, "rocksdb_block_cache_index_add_redundant": {"name": "rocksdb_block_cache_index_add_redundant", "count": 0}, "rocksdb_block_cache_filter_add_redundant": {"name": "rocksdb_block_cache_filter_add_redundant", "count": 0}, "rocksdb_block_cache_data_add_redundant": {"name": "rocksdb_block_cache_data_add_redundant", "count": 0}, "rocksdb_block_cache_compression_dict_add_redundant": {"name": "rocksdb_block_cache_compression_dict_add_redundant", "count": 0}, "rocksdb_files_marked_trash": {"name": "rocksdb_files_marked_trash", "count": 0}, "rocksdb_files_deleted_immediately": {"name": "rocksdb_files_deleted_immediately", "count": 0}, "rocksdb_db_get_micros": {"name": "rocksdb_db_get_micros", "p50": 6.200338, "p95": 13.849064, "p99": 14.963514, "p100": 6991.0, "count": 99588728, "sum": 700013583}, "rocksdb_db_write_micros": {"name": "rocksdb_db_write_micros", "p50": 3.280487, "p95": 5.644274, "p99": 8.078992, "p100": 8913.0, "count": 16403200, "sum": 64765634}, "rocksdb_compaction_times_micros": {"name": "rocksdb_compaction_times_micros", "p50": 380000.0, "p95": 455539.0, "p99": 455539.0, "p100": 455539.0, "count": 4, "sum": 1522692}, "rocksdb_compaction_times_cpu_micros": {"name": "rocksdb_compaction_times_cpu_micros", "p50": 380000.0, "p95": 421492.0, "p99": 421492.0, "p100": 421492.0, "count": 4, "sum": 1392814}, "rocksdb_subcompaction_setup_times_micros": {"name": "rocksdb_subcompaction_setup_times_micros", "p50": 0.0, "p95": 0.0, "p99": 0.0, "p100": 0.0, "count": 0, "sum": 0}, "rocksdb_table_sync_micros": {"name": "rocksdb_table_sync_micros", "p50": 306.875, "p95": 333.0, "p99": 333.0, "p100": 333.0, "count": 9, "sum": 2662}, "rocksdb_compaction_outfile_sync_micros": {"name": "rocksdb_compaction_outfile_sync_micros", "p50": 315.0, "p95": 440.0, "p99": 440.0, "p100": 440.0, "count": 4, "sum": 1371}, "rocksdb_wal_file_sync_micros": {"name": "rocksdb_wal_file_sync_micros", "p50": 0.0, "p95": 0.0, "p99": 0.0, "p100": 0.0, "count": 0, "sum": 0}, "rocksdb_manifest_file_sync_micros": {"name": "rocksdb_manifest_file_sync_micros", "p50": 2615.0, "p95": 3912.5, "p99": 4070.0, "p100": 4070.0, "count": 13, "sum": 37085}, "rocksdb_table_open_io_micros": {"name": "rocksdb_table_open_io_micros", "p50": 220.0, "p95": 667.0, "p99": 829.4, "p100": 855.0, "count": 14, "sum": 3669}, "rocksdb_db_multiget_micros": {"name": "rocksdb_db_multiget_micros", "p50": 0.0, "p95": 0.0, "p99": 0.0, "p100": 0.0, "count": 0, "sum": 0}, "rocksdb_read_block_compaction_micros": {"name": "rocksdb_read_block_compaction_micros", "p50": 0.0, "p95": 0.0, "p99": 0.0, "p100": 0.0, "count": 0, "sum": 0}, "rocksdb_read_block_get_micros": {"name": "rocksdb_read_block_get_micros", "p50": 61.80033, "p95": 115.932605, "p99": 258.008203, "p100": 6985.0, "count": 51223, "sum": 3215579}, "rocksdb_write_raw_block_micros": {"name": "rocksdb_write_raw_block_micros", "p50": 0.571558, "p95": 1.811775, "p99": 265.6, "p100": 7064.0, "count": 37772, "sum": 250162}, "rocksdb_l0_slowdown_count": {"name": "rocksdb_l0_slowdown_count", "p50": 0.0, "p95": 0.0, "p99": 0.0, "p100": 0.0, "count": 0, "sum": 0}, "rocksdb_memtable_compaction_count": {"name": "rocksdb_memtable_compaction_count", "p50": 0.0, "p95": 0.0, "p99": 0.0, "p100": 0.0, "count": 0, "sum": 0}, "rocksdb_num_files_stall_count": {"name": "rocksdb_num_files_stall_count", "p50": 0.0, "p95": 0.0, "p99": 0.0, "p100": 0.0, "count": 0, "sum": 0}, "rocksdb_hard_rate_limit_delay_count": {"name": "rocksdb_hard_rate_limit_delay_count", "p50": 0.0, "p95": 0.0, "p99": 0.0, "p100": 0.0, "count": 0, "sum": 0}, "rocksdb_soft_rate_limit_delay_count": {"name": "rocksdb_soft_rate_limit_delay_count", "p50": 0.0, "p95": 0.0, "p99": 0.0, "p100": 0.0, "count": 0, "sum": 0}, "rocksdb_numfiles_in_singlecompaction": {"name": "rocksdb_numfiles_in_singlecompaction", "p50": 2.0, "p95": 2.8, "p99": 2.96, "p100": 3.0, "count": 4, "sum": 9}, "rocksdb_db_seek_micros": {"name": "rocksdb_db_seek_micros", "p50": 7.123972, "p95": 14.425907, "p99": 19.195977, "p100": 6799.0, "count": 1171071, "sum": 9309486}, "rocksdb_db_write_stall": {"name": "rocksdb_db_write_stall", "p50": 0.500124, "p95": 0.950235, "p99": 0.990245, "p100": 1094.0, "count": 36420, "sum": 8661}, "rocksdb_sst_read_micros": {"name": "rocksdb_sst_read_micros", "p50": 67.278359, "p95": 123.859907, "p99": 318.05, "p100": 6973.0, "count": 36751, "sum": 2869105}, "rocksdb_num_subcompactions_scheduled": {"name": "rocksdb_num_subcompactions_scheduled", "p50": 0.0, "p95": 0.0, "p99": 0.0, "p100": 0.0, "count": 0, "sum": 0}, "rocksdb_bytes_per_read": {"name": "rocksdb_bytes_per_read", "p50": 0.572684, "p95": 43.0, "p99": 43.0, "p100": 43.0, "count": 99588728, "sum": 543504477}, "rocksdb_bytes_per_write": {"name": "rocksdb_bytes_per_write", "p50": 86.183225, "p95": 186.473368, "p99": 318.134054, "p100": 909.0, "count": 16403200, "sum": 1605605542}, "rocksdb_bytes_per_multiget": {"name": "rocksdb_bytes_per_multiget", "p50": 0.0, "p95": 0.0, "p99": 0.0, "p100": 0.0, "count": 0, "sum": 0}, "rocksdb_bytes_compressed": {"name": "rocksdb_bytes_compressed", "p50": 27492.992887, "p95": 32452.189723, "p99": 32893.007219, "p100": 100950.0, "count": 37746, "sum": 846236216}, "rocksdb_bytes_decompressed": {"name": "rocksdb_bytes_decompressed", "p50": 26010.462172, "p95": 32303.994986, "p99": 32863.420125, "p100": 202956.0, "count": 51223, "sum": 948732411}, "rocksdb_compression_times_nanos": {"name": "rocksdb_compression_times_nanos", "p50": 0.0, "p95": 0.0, "p99": 0.0, "p100": 0.0, "count": 0, "sum": 0}, "rocksdb_decompression_times_nanos": {"name": "rocksdb_decompression_times_nanos", "p50": 0.0, "p95": 0.0, "p99": 0.0, "p100": 0.0, "count": 0, "sum": 0}, "rocksdb_read_num_merge_operands": {"name": "rocksdb_read_num_merge_operands", "p50": 0.0, "p95": 0.0, "p99": 0.0, "p100": 0.0, "count": 0, "sum": 0}, "rocksdb_blobdb_key_size": {"name": "rocksdb_blobdb_key_size", "p50": 0.0, "p95": 0.0, "p99": 0.0, "p100": 0.0, "count": 0, "sum": 0}, "rocksdb_blobdb_value_size": {"name": "rocksdb_blobdb_value_size", "p50": 0.0, "p95": 0.0, "p99": 0.0, "p100": 0.0, "count": 0, "sum": 0}, "rocksdb_blobdb_write_micros": {"name": "rocksdb_blobdb_write_micros", "p50": 0.0, "p95": 0.0, "p99": 0.0, "p100": 0.0, "count": 0, "sum": 0}, "rocksdb_blobdb_get_micros": {"name": "rocksdb_blobdb_get_micros", "p50": 0.0, "p95": 0.0, "p99": 0.0, "p100": 0.0, "count": 0, "sum": 0}, "rocksdb_blobdb_multiget_micros": {"name": "rocksdb_blobdb_multiget_micros", "p50": 0.0, "p95": 0.0, "p99": 0.0, "p100": 0.0, "count": 0, "sum": 0}, "rocksdb_blobdb_seek_micros": {"name": "rocksdb_blobdb_seek_micros", "p50": 0.0, "p95": 0.0, "p99": 0.0, "p100": 0.0, "count": 0, "sum": 0}, "rocksdb_blobdb_next_micros": {"name": "rocksdb_blobdb_next_micros", "p50": 0.0, "p95": 0.0, "p99": 0.0, "p100": 0.0, "count": 0, "sum": 0}, "rocksdb_blobdb_prev_micros": {"name": "rocksdb_blobdb_prev_micros", "p50": 0.0, "p95": 0.0, "p99": 0.0, "p100": 0.0, "count": 0, "sum": 0}, "rocksdb_blobdb_blob_file_write_micros": {"name": "rocksdb_blobdb_blob_file_write_micros", "p50": 0.0, "p95": 0.0, "p99": 0.0, "p100": 0.0, "count": 0, "sum": 0}, "rocksdb_blobdb_blob_file_read_micros": {"name": "rocksdb_blobdb_blob_file_read_micros", "p50": 0.0, "p95": 0.0, "p99": 0.0, "p100": 0.0, "count": 0, "sum": 0}, "rocksdb_blobdb_blob_file_sync_micros": {"name": "rocksdb_blobdb_blob_file_sync_micros", "p50": 0.0, "p95": 0.0, "p99": 0.0, "p100": 0.0, "count": 0, "sum": 0}, "rocksdb_blobdb_gc_micros": {"name": "rocksdb_blobdb_gc_micros", "p50": 0.0, "p95": 0.0, "p99": 0.0, "p100": 0.0, "count": 0, "sum": 0}, "rocksdb_blobdb_compression_micros": {"name": "rocksdb_blobdb_compression_micros", "p50": 0.0, "p95": 0.0, "p99": 0.0, "p100": 0.0, "count": 0, "sum": 0}, "rocksdb_blobdb_decompression_micros": {"name": "rocksdb_blobdb_decompression_micros", "p50": 0.0, "p95": 0.0, "p99": 0.0, "p100": 0.0, "count": 0, "sum": 0}, "rocksdb_db_flush_micros": {"name": "rocksdb_db_flush_micros", "p50": 484388.0, "p95": 490736.0, "p99": 490736.0, "p100": 490736.0, "count": 7, "sum": 3418396}, "rocksdb_sst_batch_size": {"name": "rocksdb_sst_batch_size", "p50": 0.0, "p95": 0.0, "p99": 0.0, "p100": 0.0, "count": 0, "sum": 0}, "rocksdb_num_index_and_filter_blocks_read_per_level": {"name": "rocksdb_num_index_and_filter_blocks_read_per_level", "p50": 0.0, "p95": 0.0, "p99": 0.0, "p100": 0.0, "count": 0, "sum": 0}, "rocksdb_num_data_blocks_read_per_level": {"name": "rocksdb_num_data_blocks_read_per_level", "p50": 0.0, "p95": 0.0, "p99": 0.0, "p100": 0.0, "count": 0, "sum": 0}, "rocksdb_num_sst_read_per_level": {"name": "rocksdb_num_sst_read_per_level", "p50": 0.0, "p95": 0.0, "p99": 0.0, "p100": 0.0, "count": 0, "sum": 0}}, "cpu_usage": {"name": "cpu_usage", "p50": 99.9, "p95": 103.11, "p99": 104.9, "p100": 104.9, "count": 90, "sum": 8888.399999999996}, "mem_usage": {"name": "mem_usage", "p50": 0.528167724609375, "p95": 0.5564689636230469, "p99": 0.5564689636230469, "p100": 0.5564689636230469, "count": 90, "sum": 42.0776481628418}, "exe_time": 900.8966827392578}