{"db_bench": {"mixgraph": {"name": "mixgraph", "latency": 18.226, "iops": 54865.0, "io_size": 31.4}}, "compaction_statistics": {"name": "CompactionStatistics", "overall_compaction_stats": {"uptime_secs": {"total": 900.7, "interval": 300.1}, "flush_gb": {"total": 0.019, "interval": 0.0}, "addfile_gb": {"total": 0.0, "interval": 0.0}, "addfile_total_files": {"total": 0, "interval": 0}, "addfile_l0_files": {"total": 0, "interval": 0}, "addfile_keys": {"total": 0, "interval": 0}, "cumulative_compaction": {"write_size_mb": 20.0, "write_throughput": 0.02, "read_size_mb": 0.0, "read_throughput": 0.0, "time_sec": 0.1}, "interval_compaction": {"write_size_mb": 0.0, "write_throughput": 0.0, "read_size_mb": 0.0, "read_throughput": 0.0, "time_sec": 0.0}, "stalls_count": {"level0_slowdown": 0, "level0_slowdown_with_compaction": 0, "level0_numfiles": 0, "level0_numfiles_with_compaction": 0, "stop": 0, "slowdown": 0, "memtable_compaction": 0, "memtable_slowdown": 0, "total": 0}}, "per_level_compaction_stats": [{"level": 0, "in_files": 0, "out_files": 3, "size_mb": 42.61, "score": 0.2, "read_gb": 0.0, "rn_gb": 0.0, "rnp1_gb": 0.0, "write_gb": 0.0, "wnew_gb": 0.0, "moved_gb": 0.0, "w_amp": 1.0, "rd_mb_per_s": 0.0, "wr_mb_per_s": 139.7, "comp_sec": 0.14, "comp_merge_cpu_sec": 0.0, "comp_cnt": 2.0, "avg_sec": 0.068, "key_in": 0.0, "key_drop": 0.0}]}, "file_read": [{"name": "FileReadStatsLevel0", "level": 0, "count": 7768, "average": 97.9606, "stddev": 251.34, "min": 52, "median": 83.2453, "max": 8268, "p50": 83.25, "p75": 100.97, "p99": 248.51, "p99_9": 7336.56, "p99_99": 8268.0}], "statistics": {"name": "RocksDBStatistics", "rocksdb_block_cache_miss": {"name": "rocksdb_block_cache_miss", "count": 10384}, "rocksdb_block_cache_hit": {"name": "rocksdb_block_cache_hit", "count": 134379038}, "rocksdb_block_cache_add": {"name": "rocksdb_block_cache_add", "count": 10384}, "rocksdb_block_cache_add_failures": {"name": "rocksdb_block_cache_add_failures", "count": 0}, "rocksdb_block_cache_index_miss": {"name": "rocksdb_block_cache_index_miss", "count": 0}, "rocksdb_block_cache_index_hit": {"name": "rocksdb_block_cache_index_hit", "count": 0}, "rocksdb_block_cache_index_add": {"name": "rocksdb_block_cache_index_add", "count": 0}, "rocksdb_block_cache_index_bytes_insert": {"name": "rocksdb_block_cache_index_bytes_insert", "count": 0}, "rocksdb_block_cache_index_bytes_evict": {"name": "rocksdb_block_cache_index_bytes_evict", "count": 0}, "rocksdb_block_cache_filter_miss": {"name": "rocksdb_block_cache_filter_miss", "count": 0}, "rocksdb_block_cache_filter_hit": {"name": "rocksdb_block_cache_filter_hit", "count": 0}, "rocksdb_block_cache_filter_add": {"name": "rocksdb_block_cache_filter_add", "count": 0}, "rocksdb_block_cache_filter_bytes_insert": {"name": "rocksdb_block_cache_filter_bytes_insert", "count": 0}, "rocksdb_block_cache_filter_bytes_evict": {"name": "rocksdb_block_cache_filter_bytes_evict", "count": 0}, "rocksdb_block_cache_data_miss": {"name": "rocksdb_block_cache_data_miss", "count": 10384}, "rocksdb_block_cache_data_hit": {"name": "rocksdb_block_cache_data_hit", "count": 134379038}, "rocksdb_block_cache_data_add": {"name": "rocksdb_block_cache_data_add", "count": 10384}, "rocksdb_block_cache_data_bytes_insert": {"name": "rocksdb_block_cache_data_bytes_insert", "count": 76710960}, "rocksdb_block_cache_bytes_read": {"name": "rocksdb_block_cache_bytes_read", "count": 5413956046112}, "rocksdb_block_cache_bytes_write": {"name": "rocksdb_block_cache_bytes_write", "count": 76710960}, "rocksdb_bloom_filter_useful": {"name": "rocksdb_bloom_filter_useful", "count": 0}, "rocksdb_bloom_filter_full_positive": {"name": "rocksdb_bloom_filter_full_positive", "count": 0}, "rocksdb_bloom_filter_full_true_positive": {"name": "rocksdb_bloom_filter_full_true_positive", "count": 0}, "rocksdb_bloom_filter_micros": {"name": "rocksdb_bloom_filter_micros", "count": 0}, "rocksdb_persistent_cache_hit": {"name": "rocksdb_persistent_cache_hit", "count": 0}, "rocksdb_persistent_cache_miss": {"name": "rocksdb_persistent_cache_miss", "count": 0}, "rocksdb_sim_block_cache_hit": {"name": "rocksdb_sim_block_cache_hit", "count": 0}, "rocksdb_sim_block_cache_miss": {"name": "rocksdb_sim_block_cache_miss", "count": 0}, "rocksdb_memtable_hit": {"name": "rocksdb_memtable_hit", "count": 0}, "rocksdb_memtable_miss": {"name": "rocksdb_memtable_miss", "count": 41968611}, "rocksdb_l0_hit": {"name": "rocksdb_l0_hit", "count": 5362805}, "rocksdb_l1_hit": {"name": "rocksdb_l1_hit", "count": 0}, "rocksdb_l2andup_hit": {"name": "rocksdb_l2andup_hit", "count": 0}, "rocksdb_compaction_key_drop_new": {"name": "rocksdb_compaction_key_drop_new", "count": 0}, "rocksdb_compaction_key_drop_obsolete": {"name": "rocksdb_compaction_key_drop_obsolete", "count": 0}, "rocksdb_compaction_key_drop_range_del": {"name": "rocksdb_compaction_key_drop_range_del", "count": 0}, "rocksdb_compaction_key_drop_user": {"name": "rocksdb_compaction_key_drop_user", "count": 0}, "rocksdb_compaction_range_del_drop_obsolete": {"name": "rocksdb_compaction_range_del_drop_obsolete", "count": 0}, "rocksdb_compaction_optimized_del_drop_obsolete": {"name": "rocksdb_compaction_optimized_del_drop_obsolete", "count": 0}, "rocksdb_compaction_cancelled": {"name": "rocksdb_compaction_cancelled", "count": 0}, "rocksdb_number_keys_written": {"name": "rocksdb_number_keys_written", "count": 6919066}, "rocksdb_number_keys_read": {"name": "rocksdb_number_keys_read", "count": 41968611}, "rocksdb_number_keys_updated": {"name": "rocksdb_number_keys_updated", "count": 0}, "rocksdb_bytes_written": {"name": "rocksdb_bytes_written", "count": 677346936}, "rocksdb_bytes_read": {"name": "rocksdb_bytes_read", "count": 230600615}, "rocksdb_number_db_seek": {"name": "rocksdb_number_db_seek", "count": 493322}, "rocksdb_number_db_next": {"name": "rocksdb_number_db_next", "count": 278008912}, "rocksdb_number_db_prev": {"name": "rocksdb_number_db_prev", "count": 0}, "rocksdb_number_db_seek_found": {"name": "rocksdb_number_db_seek_found", "count": 493208}, "rocksdb_number_db_next_found": {"name": "rocksdb_number_db_next_found", "count": 278008910}, "rocksdb_number_db_prev_found": {"name": "rocksdb_number_db_prev_found", "count": 0}, "rocksdb_db_iter_bytes_read": {"name": "rocksdb_db_iter_bytes_read", "count": 29170432051}, "rocksdb_no_file_closes": {"name": "rocksdb_no_file_closes", "count": 0}, "rocksdb_no_file_opens": {"name": "rocksdb_no_file_opens", "count": 3}, "rocksdb_no_file_errors": {"name": "rocksdb_no_file_errors", "count": 0}, "rocksdb_l0_slowdown_micros": {"name": "rocksdb_l0_slowdown_micros", "count": 0}, "rocksdb_memtable_compaction_micros": {"name": "rocksdb_memtable_compaction_micros", "count": 0}, "rocksdb_l0_num_files_stall_micros": {"name": "rocksdb_l0_num_files_stall_micros", "count": 0}, "rocksdb_stall_micros": {"name": "rocksdb_stall_micros", "count": 0}, "rocksdb_db_mutex_wait_micros": {"name": "rocksdb_db_mutex_wait_micros", "count": 0}, "rocksdb_rate_limit_delay_millis": {"name": "rocksdb_rate_limit_delay_millis", "count": 0}, "rocksdb_num_iterators": {"name": "rocksdb_num_iterators", "count": 0}, "rocksdb_number_multiget_get": {"name": "rocksdb_number_multiget_get", "count": 0}, "rocksdb_number_multiget_keys_read": {"name": "rocksdb_number_multiget_keys_read", "count": 0}, "rocksdb_number_multiget_bytes_read": {"name": "rocksdb_number_multiget_bytes_read", "count": 0}, "rocksdb_number_deletes_filtered": {"name": "rocksdb_number_deletes_filtered", "count": 0}, "rocksdb_number_merge_failures": {"name": "rocksdb_number_merge_failures", "count": 0}, "rocksdb_bloom_filter_prefix_checked": {"name": "rocksdb_bloom_filter_prefix_checked", "count": 0}, "rocksdb_bloom_filter_prefix_useful": {"name": "rocksdb_bloom_filter_prefix_useful", "count": 0}, "rocksdb_number_reseeks_iteration": {"name": "rocksdb_number_reseeks_iteration", "count": 10058555}, "rocksdb_getupdatessince_calls": {"name": "rocksdb_getupdatessince_calls", "count": 0}, "rocksdb_block_cachecompressed_miss": {"name": "rocksdb_block_cachecompressed_miss", "count": 0}, "rocksdb_block_cachecompressed_hit": {"name": "rocksdb_block_cachecompressed_hit", "count": 0}, "rocksdb_block_cachecompressed_add": {"name": "rocksdb_block_cachecompressed_add", "count": 0}, "rocksdb_block_cachecompressed_add_failures": {"name": "rocksdb_block_cachecompressed_add_failures", "count": 0}, "rocksdb_wal_synced": {"name": "rocksdb_wal_synced", "count": 0}, "rocksdb_wal_bytes": {"name": "rocksdb_wal_bytes", "count": 677346936}, "rocksdb_write_self": {"name": "rocksdb_write_self", "count": 6919066}, "rocksdb_write_other": {"name": "rocksdb_write_other", "count": 0}, "rocksdb_write_timeout": {"name": "rocksdb_write_timeout", "count": 0}, "rocksdb_write_wal": {"name": "rocksdb_write_wal", "count": 6919066}, "rocksdb_compact_read_bytes": {"name": "rocksdb_compact_read_bytes", "count": 0}, "rocksdb_compact_write_bytes": {"name": "rocksdb_compact_write_bytes", "count": 19938233}, "rocksdb_flush_write_bytes": {"name": "rocksdb_flush_write_bytes", "count": 0}, "rocksdb_compact_read_marked_bytes": {"name": "rocksdb_compact_read_marked_bytes", "count": 0}, "rocksdb_compact_read_periodic_bytes": {"name": "rocksdb_compact_read_periodic_bytes", "count": 0}, "rocksdb_compact_read_ttl_bytes": {"name": "rocksdb_compact_read_ttl_bytes", "count": 0}, "rocksdb_compact_write_marked_bytes": {"name": "rocksdb_compact_write_marked_bytes", "count": 0}, "rocksdb_compact_write_periodic_bytes": {"name": "rocksdb_compact_write_periodic_bytes", "count": 0}, "rocksdb_compact_write_ttl_bytes": {"name": "rocksdb_compact_write_ttl_bytes", "count": 0}, "rocksdb_number_direct_load_table_properties": {"name": "rocksdb_number_direct_load_table_properties", "count": 0}, "rocksdb_number_superversion_acquires": {"name": "rocksdb_number_superversion_acquires", "count": 17}, "rocksdb_number_superversion_releases": {"name": "rocksdb_number_superversion_releases", "count": 0}, "rocksdb_number_superversion_cleanups": {"name": "rocksdb_number_superversion_cleanups", "count": 0}, "rocksdb_number_block_compressed": {"name": "rocksdb_number_block_compressed", "count": 264}, "rocksdb_number_block_decompressed": {"name": "rocksdb_number_block_decompressed", "count": 10387}, "rocksdb_number_block_not_compressed": {"name": "rocksdb_number_block_not_compressed", "count": 0}, "rocksdb_merge_operation_time_nanos": {"name": "rocksdb_merge_operation_time_nanos", "count": 0}, "rocksdb_filter_operation_time_nanos": {"name": "rocksdb_filter_operation_time_nanos", "count": 0}, "rocksdb_row_cache_hit": {"name": "rocksdb_row_cache_hit", "count": 0}, "rocksdb_row_cache_miss": {"name": "rocksdb_row_cache_miss", "count": 0}, "rocksdb_read_amp_estimate_useful_bytes": {"name": "rocksdb_read_amp_estimate_useful_bytes", "count": 0}, "rocksdb_read_amp_total_read_bytes": {"name": "rocksdb_read_amp_total_read_bytes", "count": 0}, "rocksdb_number_rate_limiter_drains": {"name": "rocksdb_number_rate_limiter_drains", "count": 0}, "rocksdb_number_iter_skip": {"name": "rocksdb_number_iter_skip", "count": 337087397}, "rocksdb_blobdb_num_put": {"name": "rocksdb_blobdb_num_put", "count": 0}, "rocksdb_blobdb_num_write": {"name": "rocksdb_blobdb_num_write", "count": 0}, "rocksdb_blobdb_num_get": {"name": "rocksdb_blobdb_num_get", "count": 0}, "rocksdb_blobdb_num_multiget": {"name": "rocksdb_blobdb_num_multiget", "count": 0}, "rocksdb_blobdb_num_seek": {"name": "rocksdb_blobdb_num_seek", "count": 0}, "rocksdb_blobdb_num_next": {"name": "rocksdb_blobdb_num_next", "count": 0}, "rocksdb_blobdb_num_prev": {"name": "rocksdb_blobdb_num_prev", "count": 0}, "rocksdb_blobdb_num_keys_written": {"name": "rocksdb_blobdb_num_keys_written", "count": 0}, "rocksdb_blobdb_num_keys_read": {"name": "rocksdb_blobdb_num_keys_read", "count": 0}, "rocksdb_blobdb_bytes_written": {"name": "rocksdb_blobdb_bytes_written", "count": 0}, "rocksdb_blobdb_bytes_read": {"name": "rocksdb_blobdb_bytes_read", "count": 0}, "rocksdb_blobdb_write_inlined": {"name": "rocksdb_blobdb_write_inlined", "count": 0}, "rocksdb_blobdb_write_inlined_ttl": {"name": "rocksdb_blobdb_write_inlined_ttl", "count": 0}, "rocksdb_blobdb_write_blob": {"name": "rocksdb_blobdb_write_blob", "count": 0}, "rocksdb_blobdb_write_blob_ttl": {"name": "rocksdb_blobdb_write_blob_ttl", "count": 0}, "rocksdb_blobdb_blob_file_bytes_written": {"name": "rocksdb_blobdb_blob_file_bytes_written", "count": 0}, "rocksdb_blobdb_blob_file_bytes_read": {"name": "rocksdb_blobdb_blob_file_bytes_read", "count": 0}, "rocksdb_blobdb_blob_file_synced": {"name": "rocksdb_blobdb_blob_file_synced", "count": 0}, "rocksdb_blobdb_blob_index_expired_count": {"name": "rocksdb_blobdb_blob_index_expired_count", "count": 0}, "rocksdb_blobdb_blob_index_expired_size": {"name": "rocksdb_blobdb_blob_index_expired_size", "count": 0}, "rocksdb_blobdb_blob_index_evicted_count": {"name": "rocksdb_blobdb_blob_index_evicted_count", "count": 0}, "rocksdb_blobdb_blob_index_evicted_size": {"name": "rocksdb_blobdb_blob_index_evicted_size", "count": 0}, "rocksdb_blobdb_gc_num_files": {"name": "rocksdb_blobdb_gc_num_files", "count": 0}, "rocksdb_blobdb_gc_num_new_files": {"name": "rocksdb_blobdb_gc_num_new_files", "count": 0}, "rocksdb_blobdb_gc_failures": {"name": "rocksdb_blobdb_gc_failures", "count": 0}, "rocksdb_blobdb_gc_num_keys_overwritten": {"name": "rocksdb_blobdb_gc_num_keys_overwritten", "count": 0}, "rocksdb_blobdb_gc_num_keys_expired": {"name": "rocksdb_blobdb_gc_num_keys_expired", "count": 0}, "rocksdb_blobdb_gc_num_keys_relocated": {"name": "rocksdb_blobdb_gc_num_keys_relocated", "count": 0}, "rocksdb_blobdb_gc_bytes_overwritten": {"name": "rocksdb_blobdb_gc_bytes_overwritten", "count": 0}, "rocksdb_blobdb_gc_bytes_expired": {"name": "rocksdb_blobdb_gc_bytes_expired", "count": 0}, "rocksdb_blobdb_gc_bytes_relocated": {"name": "rocksdb_blobdb_gc_bytes_relocated", "count": 0}, "rocksdb_blobdb_fifo_num_files_evicted": {"name": "rocksdb_blobdb_fifo_num_files_evicted", "count": 0}, "rocksdb_blobdb_fifo_num_keys_evicted": {"name": "rocksdb_blobdb_fifo_num_keys_evicted", "count": 0}, "rocksdb_blobdb_fifo_bytes_evicted": {"name": "rocksdb_blobdb_fifo_bytes_evicted", "count": 0}, "rocksdb_txn_overhead_mutex_prepare": {"name": "rocksdb_txn_overhead_mutex_prepare", "count": 0}, "rocksdb_txn_overhead_mutex_old_commit_map": {"name": "rocksdb_txn_overhead_mutex_old_commit_map", "count": 0}, "rocksdb_txn_overhead_duplicate_key": {"name": "rocksdb_txn_overhead_duplicate_key", "count": 0}, "rocksdb_txn_overhead_mutex_snapshot": {"name": "rocksdb_txn_overhead_mutex_snapshot", "count": 0}, "rocksdb_txn_get_tryagain": {"name": "rocksdb_txn_get_tryagain", "count": 0}, "rocksdb_number_multiget_keys_found": {"name": "rocksdb_number_multiget_keys_found", "count": 0}, "rocksdb_num_iterator_created": {"name": "rocksdb_num_iterator_created", "count": 493322}, "rocksdb_num_iterator_deleted": {"name": "rocksdb_num_iterator_deleted", "count": 493322}, "rocksdb_block_cache_compression_dict_miss": {"name": "rocksdb_block_cache_compression_dict_miss", "count": 0}, "rocksdb_block_cache_compression_dict_hit": {"name": "rocksdb_block_cache_compression_dict_hit", "count": 0}, "rocksdb_block_cache_compression_dict_add": {"name": "rocksdb_block_cache_compression_dict_add", "count": 0}, "rocksdb_block_cache_compression_dict_bytes_insert": {"name": "rocksdb_block_cache_compression_dict_bytes_insert", "count": 0}, "rocksdb_block_cache_compression_dict_bytes_evict": {"name": "rocksdb_block_cache_compression_dict_bytes_evict", "count": 0}, "rocksdb_block_cache_add_redundant": {"name": "rocksdb_block_cache_add_redundant", "count": 0}, "rocksdb_block_cache_index_add_redundant": {"name": "rocksdb_block_cache_index_add_redundant", "count": 0}, "rocksdb_block_cache_filter_add_redundant": {"name": "rocksdb_block_cache_filter_add_redundant", "count": 0}, "rocksdb_block_cache_data_add_redundant": {"name": "rocksdb_block_cache_data_add_redundant", "count": 0}, "rocksdb_block_cache_compression_dict_add_redundant": {"name": "rocksdb_block_cache_compression_dict_add_redundant", "count": 0}, "rocksdb_files_marked_trash": {"name": "rocksdb_files_marked_trash", "count": 0}, "rocksdb_files_deleted_immediately": {"name": "rocksdb_files_deleted_immediately", "count": 0}, "rocksdb_db_get_micros": {"name": "rocksdb_db_get_micros", "p50": 15.401563, "p95": 32.675672, "p99": 42.506208, "p100": 6870.0, "count": 41968611, "sum": 696664659}, "rocksdb_db_write_micros": {"name": "rocksdb_db_write_micros", "p50": 3.853573, "p95": 5.976861, "p99": 9.420687, "p100": 9005.0, "count": 6919066, "sum": 32189104}, "rocksdb_compaction_times_micros": {"name": "rocksdb_compaction_times_micros", "p50": 0.0, "p95": 0.0, "p99": 0.0, "p100": 0.0, "count": 0, "sum": 0}, "rocksdb_compaction_times_cpu_micros": {"name": "rocksdb_compaction_times_cpu_micros", "p50": 0.0, "p95": 0.0, "p99": 0.0, "p100": 0.0, "count": 0, "sum": 0}, "rocksdb_subcompaction_setup_times_micros": {"name": "rocksdb_subcompaction_setup_times_micros", "p50": 0.0, "p95": 0.0, "p99": 0.0, "p100": 0.0, "count": 0, "sum": 0}, "rocksdb_table_sync_micros": {"name": "rocksdb_table_sync_micros", "p50": 210.0, "p95": 217.0, "p99": 217.0, "p100": 217.0, "count": 2, "sum": 400}, "rocksdb_compaction_outfile_sync_micros": {"name": "rocksdb_compaction_outfile_sync_micros", "p50": 0.0, "p95": 0.0, "p99": 0.0, "p100": 0.0, "count": 0, "sum": 0}, "rocksdb_wal_file_sync_micros": {"name": "rocksdb_wal_file_sync_micros", "p50": 0.0, "p95": 0.0, "p99": 0.0, "p100": 0.0, "count": 0, "sum": 0}, "rocksdb_manifest_file_sync_micros": {"name": "rocksdb_manifest_file_sync_micros", "p50": 3304.0, "p95": 3304.0, "p99": 3304.0, "p100": 3304.0, "count": 2, "sum": 6332}, "rocksdb_table_open_io_micros": {"name": "rocksdb_table_open_io_micros", "p50": 140.0, "p95": 9324.0, "p99": 9324.0, "p100": 9324.0, "count": 3, "sum": 9588}, "rocksdb_db_multiget_micros": {"name": "rocksdb_db_multiget_micros", "p50": 0.0, "p95": 0.0, "p99": 0.0, "p100": 0.0, "count": 0, "sum": 0}, "rocksdb_read_block_compaction_micros": {"name": "rocksdb_read_block_compaction_micros", "p50": 0.0, "p95": 0.0, "p99": 0.0, "p100": 0.0, "count": 0, "sum": 0}, "rocksdb_read_block_get_micros": {"name": "rocksdb_read_block_get_micros", "p50": 74.48886, "p95": 181.533199, "p99": 248.411268, "p100": 6862.0, "count": 10387, "sum": 820508}, "rocksdb_write_raw_block_micros": {"name": "rocksdb_write_raw_block_micros", "p50": 7.457143, "p95": 335.428571, "p99": 546.4, "p100": 7082.0, "count": 268, "sum": 16887}, "rocksdb_l0_slowdown_count": {"name": "rocksdb_l0_slowdown_count", "p50": 0.0, "p95": 0.0, "p99": 0.0, "p100": 0.0, "count": 0, "sum": 0}, "rocksdb_memtable_compaction_count": {"name": "rocksdb_memtable_compaction_count", "p50": 0.0, "p95": 0.0, "p99": 0.0, "p100": 0.0, "count": 0, "sum": 0}, "rocksdb_num_files_stall_count": {"name": "rocksdb_num_files_stall_count", "p50": 0.0, "p95": 0.0, "p99": 0.0, "p100": 0.0, "count": 0, "sum": 0}, "rocksdb_hard_rate_limit_delay_count": {"name": "rocksdb_hard_rate_limit_delay_count", "p50": 0.0, "p95": 0.0, "p99": 0.0, "p100": 0.0, "count": 0, "sum": 0}, "rocksdb_soft_rate_limit_delay_count": {"name": "rocksdb_soft_rate_limit_delay_count", "p50": 0.0, "p95": 0.0, "p99": 0.0, "p100": 0.0, "count": 0, "sum": 0}, "rocksdb_numfiles_in_singlecompaction": {"name": "rocksdb_numfiles_in_singlecompaction", "p50": 0.0, "p95": 0.0, "p99": 0.0, "p100": 0.0, "count": 0, "sum": 0}, "rocksdb_db_seek_micros": {"name": "rocksdb_db_seek_micros", "p50": 16.859515, "p95": 33.70781, "p99": 47.411131, "p100": 6775.0, "count": 493322, "sum": 8874166}, "rocksdb_db_write_stall": {"name": "rocksdb_db_write_stall", "p50": 0.0, "p95": 0.0, "p99": 0.0, "p100": 0.0, "count": 0, "sum": 0}, "rocksdb_sst_read_micros": {"name": "rocksdb_sst_read_micros", "p50": 83.245303, "p95": 163.847134, "p99": 248.508367, "p100": 8268.0, "count": 7768, "sum": 760958}, "rocksdb_num_subcompactions_scheduled": {"name": "rocksdb_num_subcompactions_scheduled", "p50": 0.0, "p95": 0.0, "p99": 0.0, "p100": 0.0, "count": 0, "sum": 0}, "rocksdb_bytes_per_read": {"name": "rocksdb_bytes_per_read", "p50": 0.573251, "p95": 43.0, "p99": 43.0, "p100": 43.0, "count": 41968611, "sum": 230600615}, "rocksdb_bytes_per_write": {"name": "rocksdb_bytes_per_write", "p50": 86.189294, "p95": 186.495325, "p99": 318.385464, "p100": 909.0, "count": 6919066, "sum": 677346936}, "rocksdb_bytes_per_multiget": {"name": "rocksdb_bytes_per_multiget", "p50": 0.0, "p95": 0.0, "p99": 0.0, "p100": 0.0, "count": 0, "sum": 0}, "rocksdb_bytes_compressed": {"name": "rocksdb_bytes_compressed", "p50": 134560.0, "p95": 134560.0, "p99": 134560.0, "p100": 134560.0, "count": 264, "sum": 35075580}, "rocksdb_bytes_decompressed": {"name": "rocksdb_bytes_decompressed", "p50": 3669.415078, "p95": 4362.155419, "p99": 146260.769231, "p100": 202977.0, "count": 10387, "sum": 76039840}, "rocksdb_compression_times_nanos": {"name": "rocksdb_compression_times_nanos", "p50": 0.0, "p95": 0.0, "p99": 0.0, "p100": 0.0, "count": 0, "sum": 0}, "rocksdb_decompression_times_nanos": {"name": "rocksdb_decompression_times_nanos", "p50": 0.0, "p95": 0.0, "p99": 0.0, "p100": 0.0, "count": 0, "sum": 0}, "rocksdb_read_num_merge_operands": {"name": "rocksdb_read_num_merge_operands", "p50": 0.0, "p95": 0.0, "p99": 0.0, "p100": 0.0, "count": 0, "sum": 0}, "rocksdb_blobdb_key_size": {"name": "rocksdb_blobdb_key_size", "p50": 0.0, "p95": 0.0, "p99": 0.0, "p100": 0.0, "count": 0, "sum": 0}, "rocksdb_blobdb_value_size": {"name": "rocksdb_blobdb_value_size", "p50": 0.0, "p95": 0.0, "p99": 0.0, "p100": 0.0, "count": 0, "sum": 0}, "rocksdb_blobdb_write_micros": {"name": "rocksdb_blobdb_write_micros", "p50": 0.0, "p95": 0.0, "p99": 0.0, "p100": 0.0, "count": 0, "sum": 0}, "rocksdb_blobdb_get_micros": {"name": "rocksdb_blobdb_get_micros", "p50": 0.0, "p95": 0.0, "p99": 0.0, "p100": 0.0, "count": 0, "sum": 0}, "rocksdb_blobdb_multiget_micros": {"name": "rocksdb_blobdb_multiget_micros", "p50": 0.0, "p95": 0.0, "p99": 0.0, "p100": 0.0, "count": 0, "sum": 0}, "rocksdb_blobdb_seek_micros": {"name": "rocksdb_blobdb_seek_micros", "p50": 0.0, "p95": 0.0, "p99": 0.0, "p100": 0.0, "count": 0, "sum": 0}, "rocksdb_blobdb_next_micros": {"name": "rocksdb_blobdb_next_micros", "p50": 0.0, "p95": 0.0, "p99": 0.0, "p100": 0.0, "count": 0, "sum": 0}, "rocksdb_blobdb_prev_micros": {"name": "rocksdb_blobdb_prev_micros", "p50": 0.0, "p95": 0.0, "p99": 0.0, "p100": 0.0, "count": 0, "sum": 0}, "rocksdb_blobdb_blob_file_write_micros": {"name": "rocksdb_blobdb_blob_file_write_micros", "p50": 0.0, "p95": 0.0, "p99": 0.0, "p100": 0.0, "count": 0, "sum": 0}, "rocksdb_blobdb_blob_file_read_micros": {"name": "rocksdb_blobdb_blob_file_read_micros", "p50": 0.0, "p95": 0.0, "p99": 0.0, "p100": 0.0, "count": 0, "sum": 0}, "rocksdb_blobdb_blob_file_sync_micros": {"name": "rocksdb_blobdb_blob_file_sync_micros", "p50": 0.0, "p95": 0.0, "p99": 0.0, "p100": 0.0, "count": 0, "sum": 0}, "rocksdb_blobdb_gc_micros": {"name": "rocksdb_blobdb_gc_micros", "p50": 0.0, "p95": 0.0, "p99": 0.0, "p100": 0.0, "count": 0, "sum": 0}, "rocksdb_blobdb_compression_micros": {"name": "rocksdb_blobdb_compression_micros", "p50": 0.0, "p95": 0.0, "p99": 0.0, "p100": 0.0, "count": 0, "sum": 0}, "rocksdb_blobdb_decompression_micros": {"name": "rocksdb_blobdb_decompression_micros", "p50": 0.0, "p95": 0.0, "p99": 0.0, "p100": 0.0, "count": 0, "sum": 0}, "rocksdb_db_flush_micros": {"name": "rocksdb_db_flush_micros", "p50": 0.0, "p95": 0.0, "p99": 0.0, "p100": 0.0, "count": 0, "sum": 0}, "rocksdb_sst_batch_size": {"name": "rocksdb_sst_batch_size", "p50": 0.0, "p95": 0.0, "p99": 0.0, "p100": 0.0, "count": 0, "sum": 0}, "rocksdb_num_index_and_filter_blocks_read_per_level": {"name": "rocksdb_num_index_and_filter_blocks_read_per_level", "p50": 0.0, "p95": 0.0, "p99": 0.0, "p100": 0.0, "count": 0, "sum": 0}, "rocksdb_num_data_blocks_read_per_level": {"name": "rocksdb_num_data_blocks_read_per_level", "p50": 0.0, "p95": 0.0, "p99": 0.0, "p100": 0.0, "count": 0, "sum": 0}, "rocksdb_num_sst_read_per_level": {"name": "rocksdb_num_sst_read_per_level", "p50": 0.0, "p95": 0.0, "p99": 0.0, "p100": 0.0, "count": 0, "sum": 0}}, "cpu_usage": {"name": "cpu_usage", "p50": 99.9, "p95": 99.955, "p99": 100.0, "p100": 100.0, "count": 90, "sum": 8865.599999999995}, "mem_usage": {"name": "mem_usage", "p50": 0.59503173828125, "p95": 0.7874595642089843, "p99": 0.8015209197998047, "p100": 0.8048820495605469, "count": 90, "sum": 50.03602600097656}, "exe_time": 900.8365707397461}